http_dumper
